[
  {
    "type": "text",
    "text": "{\n  \"A\": {\n    \"status\": 200,\n    \"frameCount\": 1,\n    \"frames\": [\n      {\n        \"fields\": [\n          {\n            \"name\": \"definition\",\n            \"type\": \"string\"\n          }\n        ],\n        \"rowCount\": 45,\n        \"data\": [\n          [\n            \"CREATE OR REPLACE FUNCTION public.configuration_update_trigger()\\n RETURNS trigger\\n LANGUAGE plpgsql\\nAS $function$\\r\\nBEGIN\\r\\n   NOTIFY configuration_updated;\\r\\n   RETURN NEW; -- Devolver el registro modificado\\r\\nEND;\\r\\n$function$\\n\",\n            \"CREATE OR REPLACE FUNCTION public.f_offramp_payment_rd()\\n RETURNS jsonb\\n LANGUAGE plpgsql\\nAS $function$\\nBEGIN\\n  RETURN (\\n    SELECT jsonb_agg(to_jsonb(result))\\n    FROM (\\n      SELECT\\n      \\tofr.id AS \\\"offRampId\\\",\\n        CASE\\n          WHEN bl.\\\"acronym\\\" = 'BHD' THEN\\n            SUBSTRING(fa.\\\"accountNumber\\\" FROM 1 FOR 7) || '-' ||\\n            SUBSTRING(fa.\\\"accountNumber\\\" FROM 8 FOR 3) || '-' ||\\n            SUBSTRING(fa.\\\"accountNumber\\\" FROM 11 FOR 1)\\n          ELSE fa.\\\"accountNumber\\\"\\n        END AS no_cuenta,\\n        bl.\\\"acronym\\\" AS codigo_banco,\\n        CASE\\n          WHEN fa.\\\"accountType\\\"::fiat_account_accounttype_enum = 'CORRIENTE'::fiat_account_accounttype_enum THEN 'CC'\\n          ELSE 'CA'\\n        END AS tipo_cuenta,\\n        INITCAP(LOWER(ic.\\\"firstName\\\" || ' ' || ic.\\\"lastName\\\")) AS nombre_cliente,\\n        'D' AS tipo_movimiento,\\n        q.\\\"toAmount\\\"::NUMERIC AS valor_transaccion,\\n        '' AS referencia_transaccion,\\n        'Pago alfredPay' AS descripcion_transaccion,\\n        LOWER(c.email) AS email_beneficiario,\\n        CASE\\n          WHEN ic.\\\"typeDocument\\\" = 'National ID' THEN 'P'\\n          ELSE 'C'\\n        END AS tipo_identificacion,\\n        ic.dni AS numero_identificacion,\\n        'PENDING' AS status_report,\\n        CURRENT_TIMESTAMP AS date_trasaction,\\n        uuid_generate_v4() AS transacctionId\\n      FROM off_ramps ofr\\n      INNER JOIN public.quote q ON ofr.quote = q.id\\n      INNER JOIN customer c ON ofr.customer = c.id\\n      INNER JOIN individual_customers ic ON ic.\\\"customerId\\\" = c.id\\n      INNER JOIN fiat_account fa ON ofr.\\\"fiatAccount\\\" = fa.id\\n      INNER JOIN bank_list bl ON bl.name = fa.name\\n      WHERE q.\\\"toCurrency\\\" = 'DOP'\\n      AND ofr.status = 'ON_CHAIN_DEPOSIT_RECEIVED'\\n      AND ofr.\\\"txHash\\\" IS NOT NULL\\n      AND ofr.\\\"IdTransaction\\\" IS NULL\\n      --AND ofr.\\\"createdAt\\\"::DATE = CURRENT_DATE\\n    ) AS result\\n  );\\nEND;\\n$function$\\n\",\n            \"CREATE OR REPLACE FUNCTION public.f_valid_local_balance_by_customer_and_business(customer_id uuid, p_businessid numeric)\\n RETURNS jsonb\\n LANGUAGE plpgsql\\nAS $function$\\nDECLARE\\n    is_local_balance BOOLEAN;\\n    p_customer_country VARCHAR(3);\\n    response JSONB;\\nBEGIN\\n    -- Intentar obtener el balance local\\n  SELECT COALESCE(ic.country, bc.\\\"countryCode\\\")\\n  INTO p_customer_country\\n    FROM business b\\n    INNER JOIN customer c ON b.id = c.business\\n    LEFT JOIN individual_customers ic ON ic.\\\"customerId\\\" = c.id\\n    LEFT JOIN business_customers bc ON bc.\\\"customerId\\\" = c.id\\n  WHERE c.id = customer_id AND b.id = p_businessId;\\n    -- Si no se encuentra un registro, retornamos un error en JSONB\\n    IF NOT FOUND THEN\\n        RETURN jsonb_build_object(\\n            'status', 'error',\\n          \\t'statusCodeHttp', 404,\\n            'message', 'Customer not found',\\n          \\t'errorCode', 111415,\\n            'data', NULL\\n        );\\n    END IF;\\n    \\n    SELECT \\n      CASE \\n          WHEN count(*) = 1 THEN true\\n          ELSE false\\n      END AS isLocalBalancer \\n    INTO is_local_balance\\n    FROM (\\n        SELECT jsonb_array_elements(config.value::jsonb->'country') AS country_data\\n        FROM configurations config\\n        WHERE config.field = 'LOCAL_BALACE_BUSINESS_'||p_businessId\\n    ) subquery\\n    WHERE country_data->>'name' = p_customer_country\\n    AND (country_data->'status')::boolean = true;\\n\\n    -- Si el cliente no tiene balance local, retornamos otro mensaje\\n    IF is_local_balance = FALSE THEN\\n        RETURN jsonb_build_object(\\n            'status', 'error',\\n          \\t'statusCodeHttp', 404,\\n            'message', 'Customer not local balance',\\n          \\t'errorCode', 111569,\\n            'data', NULL\\n        );\\n    END IF;\\n\\n    -- Si todo está bien, devolvemos el resultado exitoso\\n    RETURN jsonb_build_object(\\n        'status', 'success',\\n        'statusCodeHttp', 200,\\n        'message', 'Customer has local balance',\\n        'data', jsonb_build_object('customer_id', customer_id, 'islocalbalance', is_local_balance, 'country', p_customer_country)\\n    );\\nEND;\\n$function$\\n\",\n            \"CREATE OR REPLACE FUNCTION public.f_valid_local_balance_by_customer_and_business(customer_id uuid, p_businessid numeric, country character varying)\\n RETURNS jsonb\\n LANGUAGE plpgsql\\nAS $function$\\nDECLARE\\n    is_local_balance BOOLEAN;\\n    p_customer_country VARCHAR(3);\\n    response JSONB;\\nBEGIN\\n    -- Intentar obtener el balance local\\n    SELECT COALESCE(ic.country, bc.\\\"countryCode\\\")\\n    INTO p_customer_country\\n      FROM business b\\n      INNER JOIN customer c ON b.id = c.business\\n      LEFT JOIN individual_customers ic ON ic.\\\"customerId\\\" = c.id\\n      LEFT JOIN business_customers bc ON bc.\\\"customerId\\\" = c.id\\n    WHERE c.id = customer_id AND b.id = p_businessId;\\n\\n    -- Si no se encuentra un registro, retornamos un error en JSONB\\n    IF NOT FOUND THEN\\n        RETURN jsonb_build_object(\\n            'status', 'error',\\n          \\t'statusCodeHttp', 404,\\n            'message', 'Customer not found',\\n          \\t'errorCode', 111415,\\n            'data', NULL\\n        );\\n    END IF;\\n    \\n    \\n    SELECT \\n      CASE \\n          WHEN COUNT(*) = 1 THEN true\\n          ELSE false\\n      END AS isLocalBalancer\\n    INTO is_local_balance\\n    FROM configurations config,\\n         jsonb_array_elements(config.value::jsonb->'country') AS elem\\n\\t\\tWHERE config.field = 'LOCAL_BALACE_BUSINESS_'||p_businessId\\n      AND elem->>'name' = UPPER(country)\\n      AND (elem->>'status') = 'true';\\n\\n    -- Si el cliente no tiene balance local, retornamos otro mensaje\\n    IF NOT FOUND THEN\\n        RETURN jsonb_build_object(\\n            'status', 'error',\\n          \\t'statusCodeHttp', 404,\\n            'message', 'Customer not VirtualAccount',\\n          \\t'errorCode', 111569,\\n            'data', NULL\\n        );\\n    END IF;\\n\\n    -- Si todo está bien, devolvemos el resultado exitoso\\n    RETURN jsonb_build_object(\\n        'status', 'success',\\n        'statusCodeHttp', 200,\\n        'message', 'Customer has local balance',\\n        'data', jsonb_build_object(\\n          'customer_id', customer_id, \\n          'islocalbalance', is_local_balance\\n        )\\n    );\\nEND;\\n$function$\\n\",\n            \"CREATE OR REPLACE FUNCTION public.find_offramp_by_bussines(p_status character varying, p_chain character varying, p_business character varying)\\n RETURNS jsonb[]\\n LANGUAGE plpgsql\\nAS $function$\\r\\nDECLARE \\r\\n    c_paymentPending jsonb;\\r\\n    c_result jsonb[] := '{}';\\r\\nBEGIN\\r\\n    FOR c_paymentPending IN \\r\\n        SELECT jsonb_build_object(\\r\\n            'id', o.id,\\r\\n            'chain', q.\\\"chain\\\",\\r\\n\\t\\t\\t'memo', o.\\\"memo\\\",\\r\\n\\t\\t\\t'fromAmount', q.\\\"fromAmount\\\",\\r\\n\\t\\t\\t'address', o.\\\"originAddress\\\"\\r\\n        )\\r\\n\\t    from \\r\\n\\toff_ramps o\\r\\ninner join \\r\\n\\tcustomer c on c.id = o.customer\\r\\ninner join\\r\\n\\t\\\"quote\\\" q on q.id = o.\\\"quote\\\"\\r\\nwhere\\r\\n\\to.\\\"createdAt\\\"::date >= current_date - 1\\r\\n\\tand c.business = p_business::numeric\\r\\n\\tand o.\\\"paymentId\\\" is null\\r\\n\\tand o.\\\"status\\\" =  p_status::off_ramps_status_enum\\r\\n\\tand q.\\\"chain\\\" = p_chain::quote_chain_enum \\r\\n\\t    ORDER BY \\r\\n\\t     \\to.\\\"createdAt\\\" ASC\\r\\n\\t    LIMIT 100\\r\\n    LOOP\\r\\n        c_result := array_append(c_result, c_paymentPending);\\r\\n    END LOOP;\\r\\n   \\r\\n    RETURN c_result;\\r\\nEND;\\r\\n$function$\\n\",\n            \"CREATE OR REPLACE FUNCTION public.find_offramp_by_bussines_and_chain_array(p_status character varying, p_chain quote_chain_enum[], p_business character varying[])\\n RETURNS jsonb[]\\n LANGUAGE plpgsql\\nAS $function$\\nDECLARE \\n    c_paymentPending jsonb;\\n    c_result jsonb[] := '{}';\\nBEGIN\\n    FOR c_paymentPending IN \\n        SELECT jsonb_build_object(\\n            'id', o.id,\\n            'chain', q.\\\"chain\\\",\\n            'memo', o.\\\"memo\\\",\\n            'fromAmount', q.\\\"fromAmount\\\",\\n            'address', o.\\\"originAddress\\\",\\n\\t\\t\\t'formCurrency', q.\\\"fromCurrency\\\",\\n\\t\\t\\t'toCurrency', q.\\\"toCurrency\\\",\\n\\t\\t\\t'paymentMethodType', q.\\\"paymentMethodType\\\",\\n\\t\\t\\t'bankCode', fa.metadata::jsonb ->> 'bankCode',\\n\\t\\t\\t'nationalIdentificationNumber', fa.metadata::jsonb ->> 'nationalIdentificationNumber',\\n\\t\\t\\t'metadata', jsonb_build_object(\\n\\t\\t\\t\\t'amount', q.\\\"toAmount\\\",\\n\\t\\t\\t\\t'recipientType', fa.metadata::jsonb ->> 'typeCustomer',\\n\\t\\t\\t\\t'senderCountry', c.\\\"type\\\",\\n\\t\\t\\t\\t'chain', q.\\\"chain\\\",\\n\\t\\t\\t\\t'paymentMethodType', q.\\\"paymentMethodType\\\",\\n\\t\\t\\t\\t'bankCode', fa.metadata::jsonb ->> 'bankCode',\\n\\t\\t\\t\\t'formCurrency', q.\\\"fromCurrency\\\",\\n\\t\\t\\t\\t'nationalIdentificationNumber', fa.metadata::jsonb ->> 'nationalIdentificationNumber',\\n\\t\\t\\t\\t'toCurrency', q.\\\"toCurrency\\\",\\n\\t            'originator', jsonb_build_object(\\n\\t                'name', COALESCE(ic.\\\"firstName\\\" || ' ' || ic.\\\"lastName\\\", bc.\\\"legalName\\\"),\\n\\t                'address', jsonb_build_object(\\n\\t                    'street', COALESCE(ic.\\\"address\\\", bc.\\\"addressStreetOne\\\"),\\n\\t                    'city', COALESCE(ic.\\\"city\\\", bc.\\\"addressCity\\\"),\\n\\t                    'country', COALESCE(ic.\\\"country\\\", bc.\\\"countryCode\\\"),\\n\\t                    'stateProvince', COALESCE(ic.\\\"state\\\", bc.\\\"stateCode\\\"),\\n\\t                    'postalCode', COALESCE(ic.\\\"zipCode\\\", bc.\\\"addressZipCode\\\")\\n\\t                ),\\n\\t                'financial', jsonb_build_object(\\n\\t                    'name', 'CELLPAY SAPI DE CV',\\n\\t                    'address', jsonb_build_object(\\n\\t                        'street', 'Av de Parque Oriente #1035',\\n\\t                        'city', 'CIUDAD DE MEXICO',\\n\\t                        'country', 'MX'\\n\\t                    )\\n\\t                )\\n\\t            ),\\n\\t            'beneficiaryAccountData', jsonb_build_object(\\n\\t                'swiftCode', fa.metadata::jsonb ->> 'swiftCode',\\n\\t                'bankName', fa.\\\"accountName\\\",\\n\\t                'country', fa.metadata::jsonb ->> 'bankCountry',\\n\\t                'accountNumber', fa.\\\"accountNumber\\\",\\n\\t                'recipientLegalName',fa.metadata::jsonb ->> 'accountHolderName'),\\n\\t            'beneficiary', jsonb_build_object(\\n\\t                'name', fa.metadata::jsonb ->> 'accountHolderName',\\n\\t                'address', jsonb_build_object(\\n\\t                    'street', fa.metadata::jsonb ->> 'bankStreet',\\n\\t                    'city', fa.metadata::jsonb ->> 'bankCity',\\n\\t                    'country', fa.metadata::jsonb ->> 'bankCountry',\\n\\t\\t\\t\\t\\t\\t'stateProvince', fa.metadata::jsonb ->> 'stateProvince',\\n\\t                    'postalCode', fa.metadata::jsonb ->> 'postalCode'\\n\\t                ),\\n\\t                'accountNumber',c.id\\n\\t            ),\\n\\t\\t\\t\\t'customerId', c.id,\\n\\t\\t\\t\\t'sendMoneyTransactionId', o.metadata::jsonb ->> 'sendMoneyTransactionId',\\n\\t\\t\\t\\t'routingNumber', COALESCE(fa.metadata::jsonb ->> 'networkIdentifier', fa.\\\"networkIdentifier\\\"),\\n\\t\\t\\t\\t'id', o.id\\n        \\t)\\n        )\\n        FROM off_ramps o\\n        INNER JOIN customer c ON c.id = o.customer\\n        INNER JOIN \\\"quote\\\" q ON q.id = o.\\\"quote\\\"\\n\\t\\tINNER JOIN fiat_account fa ON fa.id = o.\\\"fiatAccount\\\"\\n        LEFT JOIN individual_customers ic ON ic.\\\"customerId\\\" = o.customer\\n        LEFT JOIN business_customers bc ON bc.\\\"customerId\\\" = o.customer\\n        WHERE \\n\\t\\t\\t  o.\\\"createdAt\\\"::timestamp >= current_timestamp - interval '6 hours'\\n--\\t\\t\\t  o.\\\"createdAt\\\"::timestamp >= current_timestamp - interval '30 hours'\\n          AND c.business::text = ANY(p_business)\\n          AND o.\\\"paymentId\\\" IS NULL\\n\\t\\t  AND o.\\\"IdCoelsa\\\" IS NULL\\n          AND o.\\\"status\\\" = p_status::off_ramps_status_enum\\n          AND q.\\\"chain\\\" = ANY(p_chain)\\n        ORDER BY o.\\\"createdAt\\\" ASC\\n        LIMIT 100\\n    LOOP\\n        c_result := array_append(c_result, c_paymentPending);\\n    END LOOP;\\n   \\n    RETURN c_result;\\nEND;\\n$function$\\n\",\n            \"CREATE OR REPLACE FUNCTION public.find_offramps_beneficiary_info(p_business_id integer)\\n RETURNS jsonb[]\\n LANGUAGE plpgsql\\nAS $function$\\nDECLARE\\n    c_row jsonb;\\n    c_result jsonb[] := '{}';\\nBEGIN\\n    FOR c_row IN\\n        SELECT jsonb_build_object(\\n            'originator', jsonb_build_object(\\n                'name', COALESCE(ic.\\\"firstName\\\" || ' ' || ic.\\\"lastName\\\", bc.\\\"legalName\\\"),\\n                'address', jsonb_build_object(\\n                    'street', COALESCE(ic.\\\"address\\\", bc.\\\"addressStreetOne\\\"),\\n                    'city', COALESCE(ic.\\\"city\\\", bc.\\\"addressCity\\\"),\\n                    'country', COALESCE(ic.\\\"country\\\", bc.\\\"countryCode\\\"),\\n                    'stateProvince', COALESCE(ic.\\\"state\\\", bc.\\\"stateCode\\\"),\\n                    'postalCode', COALESCE(ic.\\\"zipCode\\\", bc.\\\"addressZipCode\\\")\\n                ),\\n                'financial', jsonb_build_object(\\n                    'name', 'CELLPAY SAPI DE CV',\\n                    'address', jsonb_build_object(\\n                        'street', 'Av de Parque Oriente #1035',\\n                        'city', 'CIUDAD DE MEXICO',\\n                        'country', 'MX'\\n                    )\\n                )\\n            ),\\n            'beneficiaryAccountData', jsonb_build_object(\\n                'swiftCode', fa.metadata::jsonb ->> 'swiftCode',\\n                'bankName', fa.\\\"accountName\\\",\\n                'country', fa.metadata::jsonb ->> 'bankCountry',\\n                'accountNumber', fa.\\\"accountNumber\\\",\\n                'recipientLegalName',fa.metadata::jsonb ->> 'accountHolderName'),\\n            'beneficiary', jsonb_build_object(\\n                'name', fa.metadata::jsonb ->> 'accountHolderName',\\n                'address', jsonb_build_object(\\n                    'street', fa.metadata::jsonb ->> 'bankStreet',\\n                    'city', fa.metadata::jsonb ->> 'bankCity',\\n                    'country', fa.metadata::jsonb ->> 'bankCountry'\\n                ),\\n                'accountNumber',c.id\\n            ),\\n\\t\\t\\t'customerId', c.id,\\n\\t\\t\\t'sendMoneyTransactionId', o.metadata::jsonb ->> 'sendMoneyTransactionId',\\n\\t\\t\\t'routingNumber', COALESCE(fa.metadata::jsonb ->> 'networkIdentifier', fa.\\\"networkIdentifier\\\"),\\n\\t\\t\\t'id', o.id\\n        )\\n        FROM off_ramps o\\n        INNER JOIN fiat_account fa ON fa.id = o.\\\"fiatAccount\\\"\\n        INNER JOIN customer c ON c.id = o.customer\\n        LEFT JOIN individual_customers ic ON ic.\\\"customerId\\\" = o.customer\\n        LEFT JOIN business_customers bc ON bc.\\\"customerId\\\" = o.customer\\n        WHERE \\n\\t\\t\\tc.business = p_business_id\\n\\t\\t\\tAND o.status = 'CREATED'\\n\\t\\t\\tAND o.\\\"paymentId\\\" is null \\n\\t\\t\\tAND o.metadata::jsonb ? 'sendMoneyTransactionId'\\n--\\t\\t\\tand o.id = '9352b555-f4cf-4226-b442-518454e12244'\\n\\t\\torder by o.\\\"createdAt\\\" asc\\n\\t\\tlimit 100\\n    LOOP\\n        c_result := array_append(c_result, c_row);\\n    END LOOP;\\n\\n    RETURN c_result;\\nEND;\\n$function$\\n\",\n            \"CREATE OR REPLACE FUNCTION public.find_offramps_by_status(p_status character varying, p_country character varying)\\n RETURNS jsonb[]\\n LANGUAGE plpgsql\\nAS $function$\\nDECLARE \\n    c_paymentPending jsonb;\\n    c_result jsonb[] := '{}';\\nBEGIN\\n    FOR c_paymentPending IN \\n        SELECT jsonb_build_object(\\n            'id', or2.id,\\n            'status', or2.\\\"status\\\",\\n            'city',\\n            CASE \\n                WHEN fa.\\\"isExternal\\\" = true\\n                     AND fa.metadata::jsonb ? 'bankCity'\\n                THEN fa.metadata::jsonb ->> 'bankCity'\\n                ELSE COALESCE(ic.\\\"city\\\", bc.\\\"addressCity\\\")\\n            END,\\n            'address',\\n            CASE \\n                WHEN fa.\\\"isExternal\\\" = true\\n                     AND fa.metadata::jsonb ? 'bankAddress'\\n                THEN fa.metadata::jsonb ->> 'bankAddress'\\n                ELSE COALESCE(ic.\\\"address\\\", bc.\\\"addressStreetOne\\\")\\n            END,\\n            'phone',\\n            CASE \\n                WHEN fa.\\\"isExternal\\\" = true\\n                     AND fa.metadata::jsonb ? 'phoneNumber'\\n                THEN fa.metadata::jsonb ->> 'phoneNumber'\\n                ELSE COALESCE(ic.\\\"phoneNumber\\\", bc.\\\"phoneNumber\\\")\\n            END,\\n            'createdAt', or2.\\\"createdAt\\\",\\n            'expiration', or2.\\\"expiration\\\",\\n            'memo', or2.\\\"memo\\\",\\n            'customer', or2.\\\"customer\\\",\\n            'businessId', c.\\\"business\\\",\\n            'accountNumber', fa.\\\"accountNumber\\\",\\n            'accountBankName', COALESCE(fa.\\\"name\\\", fa.\\\"accountName\\\"),\\n\\t\\t\\t'IdTransaction', or2.\\\"IdTransaction\\\" ,\\n            'accountBankType', fa.\\\"accountType\\\",\\n\\t\\t\\t'isSendMoney',COALESCE(or2.metadata::jsonb ? 'sendMoneyTransactionId', false),\\n            'typeDocument',\\n            CASE \\n                WHEN fa.\\\"isExternal\\\" = true\\n                     AND fa.metadata::jsonb ? 'documentType'\\n                THEN CASE fa.metadata::jsonb ->> 'documentType'::TEXT\\n\\t\\t\\t\\t\\tWHEN 'DNI' THEN '1'\\n                    WHEN 'PASAPORTE' THEN '3'\\n                    ELSE COALESCE(fa.metadata::jsonb ->> 'documentType'::TEXT, 'NIT')\\n\\t\\t\\t\\tEND\\n                ELSE CASE ic.\\\"typeDocumentCol\\\"::TEXT\\n                    WHEN 'DNI' THEN '1'\\n                    WHEN 'PASAPORTE' THEN '3'\\n                    ELSE COALESCE(ic.\\\"typeDocumentCol\\\"::TEXT, 'NIT')\\n                END\\n            END,\\n            'accountBankCode', fa.\\\"bankCode\\\",\\n            'amountCrypto', q.\\\"fromAmount\\\",\\n            'amountFiat', q.\\\"toAmount\\\",\\n            'firsName',\\n            CASE \\n                WHEN fa.\\\"isExternal\\\" = true\\n                     AND fa.metadata::jsonb ? 'accountHolderName'\\n                THEN fa.metadata::jsonb ->> 'accountHolderName'\\n                ELSE COALESCE(\\n                     NULLIF(ic.\\\"firstName\\\", ''),\\n                    name_parts.part1 || ' ' || name_parts.part2\\n                )\\n            END,\\n            'lastName',\\n            CASE \\n                WHEN fa.\\\"isExternal\\\" = true\\n                THEN COALESCE(fa.metadata::jsonb ->> 'accountHolderLastName', null)\\n                ELSE COALESCE(\\n                     NULLIF(ic.\\\"lastName\\\", ''),\\n                    name_parts.part3 || ' ' || name_parts.part4\\n                )\\n            END,\\n            'dni',\\n            CASE \\n                WHEN fa.\\\"isExternal\\\" = true\\n                     AND fa.metadata::jsonb ? 'documentNumber'\\n                THEN fa.metadata::jsonb ->> 'documentNumber'\\n                ELSE COALESCE(\\n                    ic.\\\"dni\\\",\\n                    REGEXP_REPLACE(bc.\\\"taxId\\\", '\\\\D', '', 'g')\\n                )\\n            END,\\n            'email',\\n            CASE \\n                WHEN fa.\\\"isExternal\\\" = true\\n                     AND fa.metadata::jsonb ? 'email'\\n                THEN fa.metadata::jsonb ->> 'email'\\n                ELSE c.email\\n            END\\n        )\\n        FROM \\n            off_ramps or2\\n        LEFT JOIN fiat_account fa ON or2.\\\"fiatAccount\\\" = fa.id\\n        LEFT JOIN quote q ON or2.\\\"quote\\\" = q.id\\n        LEFT JOIN individual_customers ic ON ic.\\\"customerId\\\" = or2.customer\\n        LEFT JOIN business_customers bc ON bc.\\\"customerId\\\" = or2.customer\\n        LEFT JOIN customer c ON c.id = or2.\\\"customer\\\"\\n        LEFT JOIN LATERAL (\\n            SELECT \\n                split[1] AS part1,\\n                split[2] AS part2,\\n                split[3] AS part3,\\n                split[4] AS part4\\n            FROM (\\n                SELECT regexp_split_to_array(bc.\\\"legalName\\\", '\\\\s+') AS split\\n            ) AS t\\n        ) name_parts ON TRUE\\n        WHERE \\n            or2.status = p_status::off_ramps_status_enum\\n            AND q.\\\"toCurrency\\\"::varchar = p_country\\n\\t\\t\\tAND or2.\\\"createdAt\\\"::date >= current_date - 30\\n\\t\\t\\tAND or2.\\\"txHash\\\" is not null\\n\\t\\t\\tand or2.metadata::jsonb ->> 'sendMoneyTransactionId' IS NULL\\n--\\t\\t\\tAND or2.id IN ('4dbc5693-4bb8-4137-ac0b-db49ab71739f')\\n        ORDER BY or2.\\\"createdAt\\\" ASC\\n        LIMIT 100\\n    LOOP\\n        c_result := array_append(c_result, c_paymentPending);\\n    END LOOP;\\n\\n    RETURN c_result;\\nEND;\\n$function$\\n\",\n            \"CREATE OR REPLACE FUNCTION public.find_offramps_by_webhook_eth(p_status character varying, p_address character varying, p_amount character varying, p_token character varying)\\n RETURNS jsonb[]\\n LANGUAGE plpgsql\\nAS $function$\\r\\nDECLARE \\r\\n    c_paymentPending jsonb;\\r\\n    c_result jsonb[] := '{}';\\r\\nBEGIN\\r\\n    FOR c_paymentPending IN \\r\\n        SELECT jsonb_build_object(\\r\\n            'id', or2.id,\\r\\n            'status', or2.\\\"status\\\",\\r\\n            'createdAt', or2.\\\"createdAt\\\",\\r\\n            'expiration', or2.\\\"expiration\\\",\\r\\n            'customer', or2.\\\"customer\\\",\\r\\n            'accountNumber', fa.\\\"accountNumber\\\",\\r\\n            'accountBankCode', fa.\\\"bankCode\\\",\\r\\n            'amountCrypto', q.\\\"fromAmount\\\",\\r\\n            'amountFiat', q.\\\"toAmount\\\",\\r\\n            'firsName', ic.\\\"firstName\\\",\\r\\n            'dni', ic.\\\"dni\\\",\\r\\n            'IdTransaction', or2.\\\"IdTransaction\\\"\\r\\n        )\\r\\n        FROM \\r\\n            off_ramps or2\\r\\n        LEFT JOIN  \\r\\n            fiat_account fa ON or2.\\\"fiatAccount\\\" = fa.id  \\r\\n        LEFT JOIN  \\r\\n            \\\"quote\\\" q on or2.\\\"quote\\\" = q.id\\r\\n        LEFT JOIN  \\r\\n            individual_customers ic on ic.\\\"customerId\\\" = or2.customer \\r\\n        WHERE \\r\\n            or2.status = p_status::off_ramps_status_enum\\r\\n\\t\\t\\tAND q.\\\"fromCurrency\\\" = p_token\\r\\n            AND trunc(q.\\\"fromAmount\\\"::numeric, 2)::varchar = trunc(p_amount::numeric, 2)::varchar\\r\\n            AND lower(or2.\\\"depositAddress\\\") = lower(p_address)\\r\\n            AND or2.\\\"createdAt\\\"::timestamp >= current_timestamp - interval '1 hours'\\r\\n        ORDER BY \\r\\n            or2.\\\"createdAt\\\" ASC\\r\\n        LIMIT 1\\r\\n    LOOP\\r\\n        c_result := array_append(c_result, c_paymentPending);\\r\\n    END LOOP;\\r\\n   \\r\\n    RETURN c_result;\\r\\nEND;\\r\\n$function$\\n\",\n            \"CREATE OR REPLACE FUNCTION public.find_offramps_by_webhook_fireblocks(p_status character varying, p_address character varying, p_amount character varying, p_memo character varying)\\n RETURNS jsonb[]\\n LANGUAGE plpgsql\\nAS $function$\\nDECLARE \\n    c_paymentPending jsonb;\\n    c_result jsonb[] := '{}';\\nBEGIN\\n    FOR c_paymentPending IN \\n        SELECT jsonb_build_object(\\n            'id', or2.id,\\n            'status', or2.\\\"status\\\",\\n            'createdAt', or2.\\\"createdAt\\\",\\n            'expiration', or2.\\\"expiration\\\",\\n            'memo', or2.\\\"memo\\\",\\n            'customer', or2.\\\"customer\\\",\\n            'accountNumber', fa.\\\"accountNumber\\\",\\n            'accountBankCode', fa.\\\"bankCode\\\",\\n            'amountCrypto', q.\\\"fromAmount\\\",\\n            'amountFiat', q.\\\"toAmount\\\",\\n\\t\\t\\t'fromCurrency', q.\\\"fromCurrency\\\",\\n\\t\\t\\t'toCurrency', q.\\\"toCurrency\\\",\\n\\t\\t\\t'chain', q.\\\"chain\\\",\\n            'firsName', ic.\\\"firstName\\\",\\n            'dni', ic.\\\"dni\\\",\\n            'IdTransaction', or2.\\\"IdTransaction\\\",\\n\\t\\t\\t'isSendMoney',COALESCE(or2.metadata::jsonb ? 'sendMoneyTransactionId', false)\\n        )\\n        FROM \\n            off_ramps or2\\n        LEFT JOIN  \\n            fiat_account fa ON or2.\\\"fiatAccount\\\" = fa.id  \\n        LEFT JOIN  \\n            \\\"quote\\\" q on or2.\\\"quote\\\" = q.id\\n        LEFT JOIN  \\n            individual_customers ic on ic.\\\"customerId\\\" = or2.customer \\n        WHERE \\n            or2.status = p_status::off_ramps_status_enum\\n            AND trunc(q.\\\"fromAmount\\\"::numeric, 2)::varchar = trunc(p_amount::numeric, 2)::varchar\\n            AND (p_memo IS NULL AND or2.memo IS NULL OR p_memo IS NOT NULL AND or2.memo = p_memo)\\n            AND lower(or2.\\\"originAddress\\\") = lower(p_address)\\n            AND or2.\\\"createdAt\\\"::timestamp >= current_timestamp - interval '24 hours'\\n        ORDER BY \\n            or2.\\\"createdAt\\\" ASC\\n        LIMIT 1\\n    LOOP\\n        c_result := array_append(c_result, c_paymentPending);\\n    END LOOP;\\n   \\n    RETURN c_result;\\nEND;\\n$function$\\n\",\n            \"CREATE OR REPLACE FUNCTION public.find_onramp_by_clabe(p_clabe character varying, p_status character varying, p_amount character varying DEFAULT NULL::character varying)\\n RETURNS jsonb\\n LANGUAGE plpgsql\\nAS $function$\\nDECLARE\\n    result JSONB;\\nBEGIN\\n    -- Intentar encontrar un registro con monto específico\\n    IF p_amount IS NOT NULL THEN\\n        SELECT jsonb_build_object(\\n            'id', o.id,\\n            'status', o.status,\\n            'amount', o.amount,\\n            'createdAt', o.\\\"createdAt\\\",\\n            'clabe', fpi.clabe,\\n\\t\\t\\t'isSendMoney',COALESCE(o.metadata::jsonb ? 'sendMoneyTransactionId', false),\\n            'quote', jsonb_build_object(\\n                'createdAt', q.\\\"createdAt\\\",\\n                'expiration', q.\\\"expiration\\\",\\n                'fromCurrency', q.\\\"fromCurrency\\\",\\n                'toCurrency', q.\\\"toCurrency\\\",\\n                'paymentMethodType', q.\\\"paymentMethodType\\\",\\n                'fromAmount', q.\\\"fromAmount\\\",\\n\\t\\t\\t\\t'toAmount', q.\\\"toAmount\\\",\\n                'chain', q.\\\"chain\\\"\\n            ),\\n            'customer', CASE\\n                WHEN c.type = 'INDIVIDUAL' THEN\\n                    jsonb_build_object(\\n                        'dni', ic.dni,\\n\\t\\t\\t\\t\\t\\t'customerName', concat(ic.\\\"firstName\\\", ' ', ic.\\\"lastName\\\"),\\n                        'businessId', jsonb_build_object(\\n                            'id', b.id\\n                        )\\n                    )\\n                ELSE\\n                    jsonb_build_object(\\n                        'dni', bc.\\\"taxId\\\",\\n\\t\\t\\t\\t\\t\\t'customerName', bc.\\\"legalName\\\",\\n                        'businessId', jsonb_build_object(\\n                            'id', b.id\\n                        )\\n                    )\\n            END\\n        )\\n        INTO result\\n        FROM on_ramps o\\n        INNER JOIN fiat_payment_instructions fpi ON fpi.id = o.\\\"fiatPaymentInstructionsId\\\"\\n        INNER JOIN quote q ON q.id = o.\\\"quote\\\"\\n\\t\\tINNER JOIN customer c ON c.id = o.customer\\n\\t\\tINNER JOIN business b on b.id = c.business\\n        LEFT JOIN individual_customers ic ON c.id = ic.\\\"customerId\\\"\\n        LEFT JOIN business_customers bc ON c.id = bc.\\\"customerId\\\"\\n        WHERE o.status = p_status::on_ramps_status_enum\\n          AND fpi.clabe = p_clabe\\n          AND o.\\\"createdAt\\\" >= current_date - INTERVAL '1 days'\\n          AND o.amount = p_amount\\n        ORDER BY o.\\\"createdAt\\\" DESC\\n        LIMIT 1;\\n    END IF;\\n\\n    -- Si no encontró resultado con monto, buscar solo por status y clabe\\n    IF result IS NULL THEN\\n        SELECT jsonb_build_object(\\n            'id', o.id,\\n            'status', o.status,\\n            'amount', o.amount,\\n            'createdAt', o.\\\"createdAt\\\",\\n            'clabe', fpi.clabe,\\n            'customer', o.customer,\\n\\t\\t\\t'isSendMoney',COALESCE(o.metadata::jsonb ? 'sendMoneyTransactionId', false),\\n            'quote', jsonb_build_object(\\n                'createdAt', q.\\\"createdAt\\\",\\n                'expiration', q.\\\"expiration\\\",\\n                'fromCurrency', q.\\\"fromCurrency\\\",\\n                'toCurrency', q.\\\"toCurrency\\\",\\n                'paymentMethodType', q.\\\"paymentMethodType\\\",\\n                'fromAmount', q.\\\"fromAmount\\\",\\n\\t\\t\\t\\t'toAmount', q.\\\"toAmount\\\",\\n                'chain', q.\\\"chain\\\"\\n            ),\\n\\t\\t\\t'customer', CASE\\n                WHEN c.type = 'INDIVIDUAL' THEN\\n                    jsonb_build_object(\\n                        'dni', ic.dni,\\n\\t\\t\\t\\t\\t\\t'customerName', concat(ic.\\\"firstName\\\", ' ', ic.\\\"lastName\\\"),\\n                        'businessId', jsonb_build_object(\\n                            'id', b.id\\n                        )\\n                    )\\n                ELSE\\n                    jsonb_build_object(\\n                        'dni', bc.\\\"taxId\\\",\\n\\t\\t\\t\\t\\t\\t'customerName', bc.\\\"legalName\\\",\\n                        'businessId', jsonb_build_object(\\n                            'id', b.id\\n                        )\\n                    )\\n            END\\n        )\\n        INTO result\\n        FROM on_ramps o\\n        INNER JOIN fiat_payment_instructions fpi ON fpi.id = o.\\\"fiatPaymentInstructionsId\\\"\\n        INNER JOIN quote q ON q.id = o.\\\"quote\\\"\\n\\t\\tINNER JOIN customer c ON c.id = o.customer\\n\\t\\tINNER JOIN business b on b.id = c.business\\n        LEFT JOIN individual_customers ic ON c.id = ic.\\\"customerId\\\"\\n        LEFT JOIN business_customers bc ON c.id = bc.\\\"customerId\\\"\\n        WHERE o.status = p_status::on_ramps_status_enum\\n          AND fpi.clabe = p_clabe\\n          AND o.\\\"createdAt\\\" >= current_date - INTERVAL '2 days'\\n        ORDER BY o.\\\"createdAt\\\" DESC\\n        LIMIT 1;\\n    END IF;\\n\\n    RETURN result;\\nEND;\\n$function$\\n\",\n            \"CREATE OR REPLACE FUNCTION public.find_onramp_by_cuit(p_status character varying, p_cuit character varying, p_amount character varying, p_fecha character varying)\\n RETURNS jsonb[]\\n LANGUAGE plpgsql\\nAS $function$\\r\\nDECLARE \\r\\n    c_paymentPending jsonb;\\r\\n    c_result jsonb[] := '{}';\\r\\nBEGIN\\r\\n    -- Primera consulta: Buscar por p_status, p_cuit y p_amount\\r\\n    FOR c_paymentPending IN \\r\\n        SELECT jsonb_build_object(\\r\\n            'id', or2.id,\\r\\n            'txHash', or2.\\\"txHash\\\",\\r\\n            'address', or2.\\\"depositAddress\\\",\\r\\n            'toAmount', q.\\\"toAmount\\\",\\r\\n            'fromAmount', q.\\\"fromAmount\\\",\\r\\n            'chain', q.\\\"chain\\\",\\r\\n            'contador', or2.\\\"totalSend\\\",\\r\\n            'reference', or2.\\\"PaymentId\\\",\\r\\n            'createdAt', or2.\\\"createdAt\\\",\\r\\n            'customerId', or2.\\\"customer\\\"\\r\\n        )\\r\\n        FROM \\r\\n           on_ramps or2 \\r\\n        INNER JOIN \\r\\n            \\\"quote\\\" q ON or2.\\\"quote\\\" = q.id\\r\\n        INNER JOIN\\r\\n            individual_customers ic on or2.customer = ic.\\\"customerId\\\"\\r\\n        WHERE \\r\\n            or2.status IN (p_status::on_ramps_status_enum)\\r\\n            AND ic.country = 'AR'\\r\\n            AND ic.dni = p_cuit\\r\\n            AND trunc(q.\\\"fromAmount\\\"::numeric, 2)::text =  p_amount::text\\r\\n            AND or2.\\\"createdAt\\\"::date >= current_date - 1\\r\\n        ORDER BY \\r\\n            or2.\\\"fiatPaymentInstructionsId\\\" ASC\\r\\n    LOOP\\r\\n        c_result := array_append(c_result, c_paymentPending);\\r\\n    END LOOP;\\r\\n\\r\\n    -- Si se encontró al menos un resultado, retornarlo\\r\\n    IF array_length(c_result, 1) > 0 THEN\\r\\n        RETURN c_result;\\r\\n    END IF;\\r\\n\\r\\n    -- Segunda consulta: Buscar solo por p_status y p_cuit\\r\\n    FOR c_paymentPending IN \\r\\n        SELECT jsonb_build_object(\\r\\n            'customerId', or2.\\\"customer\\\"\\r\\n        )\\r\\n        FROM \\r\\n           on_ramps or2\\r\\n        INNER JOIN\\r\\n            individual_customers ic on or2.customer = ic.\\\"customerId\\\"\\r\\n        WHERE \\r\\n            or2.status IN (p_status::on_ramps_status_enum)\\r\\n            AND ic.country = 'AR'\\r\\n            AND ic.dni = p_cuit\\r\\n        ORDER BY \\r\\n            or2.\\\"fiatPaymentInstructionsId\\\" ASC\\r\\n    LOOP\\r\\n        c_result := array_append(c_result, c_paymentPending);\\r\\n    END LOOP;\\r\\n\\r\\n    -- Si se encontró al menos un resultado en la segunda consulta, retornarlo\\r\\n    IF array_length(c_result, 1) > 0 THEN\\r\\n        RETURN c_result;\\r\\n    END IF;\\r\\n\\r\\n    -- Si no se encontró ningún resultado, retornar vacío\\r\\n    RETURN '{}';\\r\\nEND;\\r\\n$function$\\n\",\n            \"CREATE OR REPLACE FUNCTION public.find_onramp_by_cuit_kyc_kyb(p_status character varying, p_cuit character varying, p_amount character varying)\\n RETURNS jsonb[]\\n LANGUAGE plpgsql\\nAS $function$\\nDECLARE\\n    c_payment jsonb;\\n    c_result jsonb[] := ARRAY[]::jsonb[];\\nBEGIN\\n    -- Primera búsqueda: filtrando por monto\\n    FOR c_payment IN\\n        SELECT jsonb_build_object(\\n            'id', or2.id,\\n            'txHash', or2.\\\"txHash\\\",\\n            'address', or2.\\\"depositAddress\\\",\\n            'toAmount', q.\\\"toAmount\\\",\\n            'fromAmount', q.\\\"fromAmount\\\",\\n            'chain', q.\\\"chain\\\",\\n            'contador', or2.\\\"totalSend\\\",\\n            'reference', or2.\\\"PaymentId\\\",\\n            'createdAt', or2.\\\"createdAt\\\",\\n            'customerId', or2.customer,\\n            'condicion 1', 'hola 1'\\n        )\\n        FROM on_ramps or2\\n        INNER JOIN \\\"quote\\\" q ON or2.\\\"quote\\\" = q.id\\n        LEFT JOIN individual_customers ic ON ic.\\\"customerId\\\" = or2.customer\\n        LEFT JOIN business_customers bc ON bc.\\\"customerId\\\" = or2.customer\\n        WHERE or2.status IN (p_status::on_ramps_status_enum)\\n          AND COALESCE(ic.\\\"country\\\", bc.\\\"countryCode\\\", '') = 'AR'\\n          AND ((ic.dni IS NOT NULL AND ic.dni = p_cuit) OR (bc.\\\"taxId\\\" IS NOT NULL AND bc.\\\"taxId\\\" = p_cuit))\\n          AND trunc(q.\\\"fromAmount\\\"::numeric, 2)::text = trunc(p_amount::numeric, 2)::text\\n        ORDER BY or2.\\\"fiatPaymentInstructionsId\\\" ASC\\n        LIMIT 1\\n    LOOP\\n        c_result := array_append(c_result, c_payment);\\n    END LOOP;\\n\\n    -- Si no encontró resultados, busca nuevamente sin filtrar por monto\\n    IF array_length(c_result, 1) IS NULL THEN\\n        FOR c_payment IN\\n            SELECT jsonb_build_object(\\n                'id', or2.id,\\n                'txHash', or2.\\\"txHash\\\",\\n                'address', or2.\\\"depositAddress\\\",\\n                'toAmount', q.\\\"toAmount\\\",\\n                'fromAmount', q.\\\"fromAmount\\\",\\n                'chain', q.\\\"chain\\\",\\n                'contador', or2.\\\"totalSend\\\",\\n                'reference', or2.\\\"PaymentId\\\",\\n                'createdAt', or2.\\\"createdAt\\\",\\n                'customerId', or2.customer,\\n                'condicion 2', 'hola 2'\\n            )\\n            FROM on_ramps or2\\n            INNER JOIN \\\"quote\\\" q ON or2.\\\"quote\\\" = q.id\\n            LEFT JOIN individual_customers ic ON ic.\\\"customerId\\\" = or2.customer\\n            LEFT JOIN business_customers bc ON bc.\\\"customerId\\\" = or2.customer\\n            WHERE or2.status IN (p_status::on_ramps_status_enum)\\n              AND COALESCE(ic.\\\"country\\\", bc.\\\"countryCode\\\", '') = 'AR'\\n              AND ((ic.dni IS NOT NULL AND ic.dni = p_cuit) OR (bc.\\\"taxId\\\" IS NOT NULL AND bc.\\\"taxId\\\" = p_cuit))\\n            ORDER BY or2.\\\"fiatPaymentInstructionsId\\\" ASC\\n            LIMIT 1\\n        LOOP\\n            c_result := array_append(c_result, c_payment);\\n        END LOOP;\\n    END IF;\\n\\n    RETURN c_result;\\nEND;\\n$function$\\n\",\n            \"CREATE OR REPLACE FUNCTION public.find_onramp_reject()\\n RETURNS jsonb[]\\n LANGUAGE plpgsql\\nAS $function$\\r\\nDECLARE \\r\\n    c_paymentPending jsonb;\\r\\n    c_result jsonb[] := '{}';\\r\\nBEGIN\\r\\n    FOR c_paymentPending IN \\r\\n        SELECT jsonb_build_object(\\r\\n            'id', or2.id,\\r\\n            'txHash', or2.\\\"txHash\\\",\\r\\n            'address', or2.\\\"depositAddress\\\",\\r\\n            'toAmount', q.\\\"toAmount\\\",\\r\\n \\t\\t\\t'fromAmount', q.\\\"fromAmount\\\",\\r\\n            'chain', q.\\\"chain\\\",\\r\\n            'contador', or2.\\\"totalSend\\\",\\r\\n\\t\\t\\t'refenrence', or2.\\\"PaymentId\\\"\\r\\n        )\\r\\n\\t    FROM \\r\\n\\t       on_ramps or2 \\r\\n\\t    INNER JOIN \\r\\n\\t        \\\"quote\\\" q ON or2.\\\"quote\\\" = q.id\\r\\n\\t    WHERE \\r\\n\\t\\t\\tor2.status = 'CREATED'\\r\\n\\t\\t\\tAND or2.\\\"createdAt\\\"::timestamp < current_timestamp - INTERVAL '1 hours'\\r\\n\\t    ORDER BY \\r\\n\\t     \\tor2.\\\"fiatPaymentInstructionsId\\\" ASC\\r\\n\\t    LIMIT 500\\r\\n    LOOP\\r\\n        c_result := array_append(c_result, c_paymentPending);\\r\\n    END LOOP;\\r\\n   \\r\\n    RETURN c_result;\\r\\nEND;\\r\\n$function$\\n\",\n            \"CREATE OR REPLACE FUNCTION public.find_payouts_local_balance_by_status_and_currency(p_status character varying, p_currency character varying)\\n RETURNS jsonb[]\\n LANGUAGE plpgsql\\nAS $function$\\r\\nDECLARE\\r\\n    c_payout jsonb;\\r\\n    c_result jsonb[] := '{}';\\r\\nBEGIN\\r\\n    FOR c_payout IN\\r\\n        SELECT jsonb_build_object(\\r\\n            'id', p.id,\\r\\n            'amount', p.amount,\\r\\n            'accountOrigen', p.payer_account_number,\\r\\n            'nameOrigen', p.beneficiary_name,\\r\\n            'accountDestiny', p.account_identifier_value,\\r\\n            'status', p.status,\\r\\n            'createdAt', p.created_at,\\r\\n\\t\\t\\t'referenceId', p.request_reference_id\\r\\n        )\\r\\n        FROM payout p\\r\\n        WHERE p.status = p_status::payout_status_enum\\r\\n          AND p.currency = p_currency\\r\\n        ORDER BY p.created_at DESC\\r\\n    LOOP\\r\\n        c_result := array_append(c_result, c_payout);\\r\\n    END LOOP;\\r\\n\\r\\n    RETURN c_result;\\r\\nEND;\\r\\n$function$\\n\",\n            \"CREATE OR REPLACE FUNCTION public.find_refund_transfers_by_status(p_status character varying)\\n RETURNS jsonb[]\\n LANGUAGE plpgsql\\nAS $function$\\r\\nDECLARE\\r\\n    c_transfer jsonb;\\r\\n    c_result jsonb[] := '{}';\\r\\nBEGIN\\r\\n    FOR c_transfer IN\\r\\n        SELECT jsonb_build_object(\\r\\n            'currency', r.currency,\\r\\n            'accountDestiny', p.debtor_account_identifier_value,\\r\\n            'amount', r.amount,\\n\\t\\t\\t'nameOrigen',p.debtor_name,\\n\\t\\t\\t'accountOrigen',p.customer_id,\\r\\n\\t\\t\\t'id',r.id\\r\\n        )\\r\\n\\t\\tFROM refund r\\r\\n\\t\\tinner join payin p on p.system_reference = r.system_reference and r.refund_request_id = p.request_id\\r\\n\\t\\tWHERE r.status = p_status::refund_status_v2\\r\\n\\t\\tORDER BY r.created_at DESC\\r\\n    LOOP\\r\\n        c_result := array_append(c_result, c_transfer);\\r\\n    END LOOP;\\r\\n\\r\\n    RETURN c_result;\\r\\nEND;\\r\\n$function$\\n\",\n            \"CREATE OR REPLACE FUNCTION public.find_transfers_swap_by_status(p_status character varying)\\n RETURNS jsonb[]\\n LANGUAGE plpgsql\\nAS $function$\\r\\nDECLARE\\r\\n    c_transfer jsonb;\\r\\n    c_result jsonb[] := '{}';\\r\\nBEGIN\\r\\n    FOR c_transfer IN\\r\\n        SELECT jsonb_build_object(\\r\\n            'fromCurrency', qv.from_currency,\\r\\n            'toCurrency', qv.to_currency,\\r\\n            'fromAccount', t.from_account_id,\\r\\n            'toAccount', t.to_account_id,\\r\\n            'fromAmount', qv.from_amount,\\r\\n            'toAmount', qv.to_amount,\\n\\t\\t\\t'referenceId', t.external_reference\\r\\n        )\\r\\n        FROM transfer t\\r\\n        INNER JOIN quote_v2 qv ON qv.id = t.quote_id\\r\\n        WHERE t.status = p_status::transfer_status_enum \\r\\n        ORDER BY t.created_at DESC\\r\\n    LOOP\\r\\n        c_result := array_append(c_result, c_transfer);\\r\\n    END LOOP;\\r\\n\\r\\n    RETURN c_result;\\r\\nEND;\\r\\n$function$\\n\",\n            \"CREATE OR REPLACE FUNCTION public.findonrampbyrejectedandcurrency(p_status character varying, p_currency character varying)\\n RETURNS jsonb[]\\n LANGUAGE plpgsql\\nAS $function$\\r\\nDECLARE \\r\\n    c_paymentPending jsonb;\\r\\n    c_result jsonb[] := '{}';\\r\\nBEGIN\\r\\n    FOR c_paymentPending IN \\r\\n        SELECT jsonb_build_object(\\r\\n            'id', or2.id,\\r\\n            'txHash', or2.\\\"txHash\\\",\\r\\n            'address', or2.\\\"depositAddress\\\",\\r\\n            'toAmount', q.\\\"toAmount\\\",\\r\\n            'chain', or2.\\\"chain\\\",\\r\\n            'totalSend', or2.\\\"totalSend\\\"\\r\\n        )\\r\\n\\t    FROM \\r\\n\\t       on_ramps or2 \\r\\n\\t    INNER JOIN \\r\\n\\t        \\\"quote\\\" q ON or2.\\\"quote\\\" = q.id\\r\\n\\t    WHERE \\r\\n\\t\\t\\tor2.status = p_status::on_ramps_status_enum\\r\\n\\t\\t\\tAND (or2.\\\"txHash\\\" is null OR or2.\\\"txHash\\\" = '')\\r\\n\\t\\t\\tAND or2.\\\"totalSend\\\" = 1\\r\\n\\t\\t\\tAND or2.\\\"fromCurrency\\\"::varchar = p_currency::varchar\\r\\n\\t\\t\\tAND or2.\\\"createdAt\\\" < CURRENT_TIMESTAMP - INTERVAL '30 minutes'\\r\\n\\t    ORDER BY \\r\\n\\t     \\tor2.\\\"fiatPaymentInstructionsId\\\" ASC\\r\\n\\t    LIMIT 500\\r\\n    LOOP\\r\\n        c_result := array_append(c_result, c_paymentPending);\\r\\n    END LOOP;\\r\\n   \\r\\n    RETURN c_result;\\r\\nEND;\\r\\n$function$\\n\",\n            \"CREATE OR REPLACE FUNCTION public.findonrampbystatusandcurrency(p_action integer, p_status character varying, p_currency character varying)\\n RETURNS jsonb[]\\n LANGUAGE plpgsql\\nAS $function$\\nDECLARE \\n    c_paymentPending jsonb;\\n    c_result jsonb[] := '{}';\\nBEGIN\\n     FOR c_paymentPending IN \\n        SELECT jsonb_build_object(\\n            'id', or2.id,\\n            'txHash', or2.\\\"txHash\\\",\\n            'address', or2.\\\"depositAddress\\\",\\n            'toAmount', q.\\\"toAmount\\\",\\n            'chain', q.\\\"chain\\\",\\n            'contador', or2.\\\"totalSend\\\",\\n\\t\\t\\t'memo', or2.\\\"memo\\\",\\n\\t\\t\\t'customerId', or2.\\\"customer\\\",\\n\\t\\t\\t'fromAmount', or2.\\\"amount\\\",\\n\\t\\t\\t'nameUser', COALESCE(ic.\\\"firstName\\\" || ' ' || ic.\\\"lastName\\\", bc.\\\"legalName\\\"),\\n\\t\\t\\t'email', c.email,\\n\\t\\t\\t'currency', q.\\\"toCurrency\\\",\\n\\t\\t\\t'isSendMoney',COALESCE(or2.metadata::jsonb ? 'sendMoneyTransactionId', false)\\n        )\\n\\t    FROM \\n\\t       on_ramps or2 \\n\\t    INNER JOIN \\n\\t        \\\"quote\\\" q ON or2.\\\"quote\\\" = q.id\\n\\t\\tLEFT JOIN \\n\\t\\t\\tindividual_customers ic ON ic.\\\"customerId\\\" = or2.\\\"customer\\\"\\n        LEFT JOIN \\n\\t\\t\\tbusiness_customers bc ON bc.\\\"customerId\\\" = or2.\\\"customer\\\"\\n\\t\\tINNER JOIN \\n\\t\\t\\tcustomer c on or2.customer = c.id \\n\\t    WHERE \\n\\t        or2.\\\"fiatPaymentInstructionsId\\\" % 2 = p_action\\n\\t\\t\\tAND or2.status = p_status::on_ramps_status_enum\\n\\t\\t\\tAND q.\\\"fromCurrency\\\"::varchar = p_currency::varchar\\n\\t\\t\\tand or2.\\\"totalSend\\\" = 0\\n\\t\\t\\tAND or2.\\\"createdAt\\\"::date >= current_date - 7\\n--\\t\\t\\tand or2.id =''\\n\\t    ORDER BY \\n\\t     \\tor2.\\\"fiatPaymentInstructionsId\\\" ASC\\n\\t    LIMIT 100\\n    LOOP\\n        c_result := array_append(c_result, c_paymentPending);\\n    END LOOP;\\n   \\n    RETURN c_result;\\nEND;\\n$function$\\n\",\n            \"CREATE OR REPLACE FUNCTION public.fn_get_account_validation(p_account character varying, p_country character varying, p_provider_name character varying)\\n RETURNS jsonb\\n LANGUAGE plpgsql\\nAS $function$\\r\\nDECLARE\\r\\n    result JSONB;\\r\\nBEGIN\\r\\n    SELECT response\\r\\n    INTO result\\r\\n    FROM account_validation_cache\\r\\n    WHERE country_code = p_country\\r\\n      AND (\\r\\n            account_number = p_account\\r\\n         OR account_alias = p_account\\r\\n      )\\r\\n      AND provider_name = p_provider_name\\r\\n      AND active IS DISTINCT FROM FALSE   -- acepta NULL o TRUE\\r\\n    LIMIT 1;\\r\\n\\r\\n    RETURN result;\\r\\nEND;\\r\\n$function$\\n\",\n            \"CREATE OR REPLACE FUNCTION public.fn_insert_account_validation(p_account_number character varying, p_account_alias character varying, p_response jsonb, p_provider_name character varying, p_country_code character varying, p_active boolean DEFAULT true)\\n RETURNS text\\n LANGUAGE plpgsql\\nAS $function$\\r\\nBEGIN\\r\\n    INSERT INTO account_validation_cache (\\r\\n        account_number,\\r\\n        account_alias,\\r\\n        response,\\r\\n        provider_name,\\r\\n        country_code,\\r\\n        active,\\r\\n        created_at,\\r\\n        updated_at\\r\\n    ) VALUES (\\r\\n        p_account_number,\\r\\n        p_account_alias,\\r\\n        p_response,\\r\\n        p_provider_name,\\r\\n        p_country_code,\\r\\n        p_active,\\r\\n        NOW(),\\r\\n        NOW()\\r\\n    );\\r\\n\\r\\n    RETURN 'OK';\\r\\nEXCEPTION\\r\\n    WHEN OTHERS THEN\\r\\n        RETURN SQLERRM;  -- Devuelve el mensaje de error\\r\\nEND;\\r\\n$function$\\n\",\n            \"CREATE OR REPLACE FUNCTION public.get_customer_off_ramps_sums(customer_id uuid)\\n RETURNS TABLE(daily_sum numeric, monthly_sum numeric)\\n LANGUAGE plpgsql\\nAS $function$\\r\\nBEGIN\\r\\n    RETURN QUERY\\r\\n    select sum(\\r\\n\\t\\tcase\\r\\n\\t\\t\\twhen off_ramps.\\\"createdAt\\\"::date = current_date  then q.\\\"fromAmount\\\"::numeric\\r\\n\\t\\t\\telse 0::numeric \\r\\n\\t\\tend\\r\\n\\t\\t\\r\\n\\t\\t)as \\\"daily_sum\\\",\\r\\n\\t\\tsum(q.\\\"fromAmount\\\"::numeric) as \\\"monthly_sum\\\"\\r\\n\\tfrom off_ramps \\r\\n\\tleft join \\\"quote\\\" q  on  off_ramps.\\\"quote\\\" = q.id\\r\\n\\tWHERE off_ramps.status = 'FIAT_TRANSFER_COMPLETED'\\r\\n\\tand to_char(off_ramps.\\\"createdAt\\\", 'YYYY-MM') = to_char(current_date, 'YYYY-MM')\\r\\n\\tAND off_ramps.customer = customer_id\\r\\n\\tgroup by off_ramps.customer;\\r\\n\\tEND;\\r\\n$function$\\n\",\n            \"CREATE OR REPLACE FUNCTION public.get_customer_onramp_sums(customer_id uuid)\\n RETURNS TABLE(daily_sum numeric, monthly_sum numeric)\\n LANGUAGE plpgsql\\nAS $function$\\r\\nBEGIN\\r\\n    RETURN QUERY\\r\\n    SELECT \\r\\n        sum(\\r\\n            CASE\\r\\n                WHEN on_ramps.\\\"createdAt\\\"::DATE = CURRENT_DATE THEN on_ramps.amount::numeric\\r\\n                ELSE 0::numeric\\r\\n            END) AS daily_sum,\\r\\n        sum(on_ramps.amount::numeric) AS monthly_sum\\r\\n    FROM on_ramps\\r\\n    WHERE on_ramps.status = 'ON_CHAIN_COMPLETED'::on_ramps_status_enum \\r\\n    AND on_ramps.\\\"paymentMethodType\\\" = 'ARS_BANK_TRANSFER'::on_ramps_paymentmethodtype_enum\\r\\n    AND to_char(on_ramps.\\\"createdAt\\\", 'YYYY-MM') = to_char(current_date, 'YYYY-MM')\\r\\n    AND on_ramps.customer = customer_id\\r\\n    GROUP BY on_ramps.customer;\\r\\nEND;\\r\\n$function$\\n\",\n            \"CREATE OR REPLACE FUNCTION public.get_onramp_data_by_cpf(p_from_currency character varying, p_tax_id character varying, p_from_amount character varying, p_status character varying)\\n RETURNS jsonb[]\\n LANGUAGE plpgsql\\nAS $function$\\r\\nDECLARE\\r\\n    c_row jsonb;\\r\\n    c_result jsonb[] := '{}';\\r\\nBEGIN\\r\\n    FOR c_row IN\\r\\n        SELECT jsonb_build_object(\\r\\n                   'id', or2.id,\\r\\n                   'status', or2.\\\"status\\\",\\r\\n                   'createdAt', or2.\\\"createdAt\\\",\\r\\n                   'customer', or2.\\\"customer\\\",\\r\\n                   'amountCrypto', q.\\\"fromAmount\\\",\\r\\n                   'amountFiat', q.\\\"toAmount\\\",\\r\\n                   'dni', REGEXP_REPLACE(bc.\\\"taxId\\\", '[^0-9]', '', 'g')\\r\\n               )\\r\\n        FROM on_ramps or2\\r\\n        INNER JOIN quote q ON or2.quote = q.id\\r\\n        INNER JOIN business_customers bc ON bc.\\\"customerId\\\" = or2.customer\\r\\n        INNER JOIN customer c ON or2.customer = c.id\\r\\n        WHERE q.\\\"fromCurrency\\\"::TEXT = p_from_currency::TEXT\\r\\n          AND REGEXP_REPLACE(bc.\\\"taxId\\\", '[^0-9]', '', 'g')::TEXT = p_tax_id::TEXT\\r\\n          AND q.\\\"fromAmount\\\"::TEXT = p_from_amount::TEXT\\r\\n\\t\\t  AND or2.\\\"status\\\"::text = p_status::text\\n\\t\\t  AND or2.\\\"PaymentGroupId\\\" is null\\r\\n          AND or2.\\\"totalSend\\\" = 0\\r\\n          AND or2.\\\"createdAt\\\" >= NOW() - INTERVAL '2 hours'\\r\\n        ORDER BY or2.\\\"createdAt\\\" ASC\\r\\n    LOOP\\r\\n        c_result := array_append(c_result, c_row);\\r\\n    END LOOP;\\r\\n\\r\\n    RETURN c_result;\\r\\nEND;\\r\\n$function$\\n\",\n            \"CREATE OR REPLACE FUNCTION public.get_onramp_data_by_cpf_and_reference(p_from_currency character varying, p_tax_id character varying, p_from_amount character varying, p_status character varying, p_reference character varying)\\n RETURNS jsonb[]\\n LANGUAGE plpgsql\\nAS $function$\\r\\nDECLARE\\r\\n    c_row jsonb;\\r\\n    c_result jsonb[] := '{}';\\r\\n    v_exists boolean;\\r\\nBEGIN\\r\\n    -- 🔍 Verificar si ya existe el reference\\r\\n    SELECT TRUE INTO v_exists\\r\\n    FROM on_ramps or2\\r\\n    LEFT JOIN fiat_payment_instructions fpi ON or2.\\\"fiatPaymentInstructionsId\\\" = fpi.id\\r\\n    WHERE fpi.reference = p_reference\\r\\n    LIMIT 1;\\r\\n\\r\\n    -- 🚫 Si existe, retornar vacío inmediatamente\\r\\n    IF v_exists THEN\\r\\n        RETURN '{}';\\r\\n    END IF;\\r\\n\\r\\n    -- ✅ Continuar con la búsqueda normal\\r\\n    FOR c_row IN\\r\\n        SELECT jsonb_build_object(\\r\\n                   'id', or2.id,\\r\\n                   'status', or2.\\\"status\\\",\\r\\n                   'createdAt', or2.\\\"createdAt\\\",\\r\\n                   'customer', or2.\\\"customer\\\",\\r\\n                   'amountCrypto', q.\\\"fromAmount\\\",\\r\\n                   'amountFiat', q.\\\"toAmount\\\",\\r\\n                   'dni', REGEXP_REPLACE(COALESCE(bc.\\\"taxId\\\", ic.dni), '[^0-9]', '', 'g')\\r\\n               )\\r\\n        FROM on_ramps or2\\r\\n        INNER JOIN quote q ON or2.quote = q.id\\r\\n        LEFT JOIN business_customers bc ON bc.\\\"customerId\\\" = or2.customer\\r\\n        LEFT JOIN individual_customers ic ON ic.\\\"customerId\\\" = or2.customer\\r\\n        INNER JOIN customer c ON or2.customer = c.id\\r\\n        WHERE q.\\\"fromCurrency\\\"::TEXT = p_from_currency::TEXT\\r\\n          AND REGEXP_REPLACE(COALESCE(bc.\\\"taxId\\\", ic.dni), '[^0-9]', '', 'g')::TEXT = p_tax_id::TEXT\\r\\n          AND q.\\\"fromAmount\\\"::TEXT = p_from_amount::TEXT\\r\\n          AND or2.\\\"status\\\"::TEXT = p_status::TEXT\\r\\n          AND or2.\\\"PaymentGroupId\\\" IS NULL\\r\\n          AND or2.\\\"totalSend\\\" = 0\\r\\n          AND or2.\\\"createdAt\\\" >= NOW() - INTERVAL '2 hours'\\r\\n        ORDER BY or2.\\\"createdAt\\\" ASC\\r\\n    LOOP\\r\\n        c_result := array_append(c_result, c_row);\\r\\n    END LOOP;\\r\\n\\r\\n    RETURN c_result;\\r\\nEND;\\r\\n$function$\\n\",\n            \"CREATE OR REPLACE FUNCTION public.get_tx(p_id integer)\\n RETURNS boolean\\n LANGUAGE plpgsql\\nAS $function$\\r\\ndeclare\\r\\n    v_tx varchar;\\r\\n    v_id_blockchain float;\\r\\n    v_exist boolean = false;\\r\\n\\tv_address varchar;\\r\\n\\tv_amount integer = 0;\\r\\n\\tv_fec varchar;\\r\\n\\r\\nbegin\\r\\n\\tRAISE NOTICE 'Init whitdrawID: %',p_id;\\r\\n\\tif (p_id is null) then \\n\\t\\tRAISE NOTICE 'Init whitdrawID is null: %',p_id;\\r\\n\\t\\tv_exist = false;\\r\\n\\t\\treturn v_exist; \\r\\n\\tend if;\\r\\n\\t/*\\r\\n\\t* Process: Identificion de transacion alfredPay.\\r\\n\\t* Descripcion: este proceso permite ubicar la transaccion con el fin\\r\\n\\t* de validar si la mima se rechaza o no en tal caso de que no consiga merge con la tabla contract_event.\\r\\n\\t*/\\r\\n\\tSELECT bi.address, cast(w.\\\"createdAt\\\" as timestamp) AS fec, t.amount\\r\\n\\tINTO v_address, v_fec, v_amount\\r\\n\\tFROM withdraw w\\r\\n\\tJOIN transacction t ON w.\\\"transacctionId\\\" = t.id\\r\\n\\tJOIN invoice i ON t.\\\"invoiceId\\\" = i.id\\r\\n\\tJOIN business_interaction bi ON i.\\\"businessInteractionId\\\" = bi.id\\r\\n\\tWHERE w.id = p_id;\\r\\n\\r\\n\\tRAISE NOTICE 'Transaction value v_address % v_fec % v_amount %', v_address, v_fec, v_amount;\\r\\n\\r\\n\\tSELECT tx, id \\r\\n\\tINTO v_tx, v_id_blockchain \\r\\n\\tFROM contract_event \\r\\n\\tWHERE lower(\\\"from\\\")=lower(v_address) \\r\\n\\tAND amount::numeric / 1000000000000000000 =v_amount\\r\\n\\tAND \\\"date\\\" is not null\\r\\n\\tAND cast(\\\"date\\\" as timestamp) at time zone 'utc' >= v_fec\\r\\n--\\tAND (extract(epoch from cast(\\\"date\\\" as timestamp)) - extract(epoch from v_fec)) < 18000\\r\\n\\tAND id not in (select id_blockchain from test_scripts) \\r\\n\\tAND NOT EXISTS (\\n\\t    SELECT 1\\n\\t    FROM transacction t\\n\\t    JOIN invoice i ON t.\\\"invoiceId\\\" = i.id\\n\\t    JOIN business_interaction bi ON i.\\\"businessInteractionId\\\" = bi.id\\n\\t    WHERE lower(bi.address) = lower('0xDbF06edaCbC14E6082105329893C71040E0A4e40')\\n\\t    AND tx = t.\\\"txHash\\\"\\n--\\t    AND t.\\\"createdAt\\\" >= '2024-04-11 22:38:21.000 -0400'\\n\\t)\\r\\n\\tLIMIT 1;\\n\\r\\n\\tRAISE NOTICE 'Transaction txHash % v_id_blockchain %', v_tx, v_id_blockchain;\\r\\n\\tif (v_tx is not null) then \\r\\n\\r\\n\\t\\tv_exist = true;\\r\\n\\t\\tinsert into test_scripts \\r\\n\\t\\t(id, tx, id_blockchain, fecha) values(p_id, v_tx, v_id_blockchain, cast(v_fec as date)); \\r\\n\\r\\n\\t\\tupdate transacction \\r\\n\\t\\tset \\\"txHash\\\" = v_tx  where \\\"withdrawId\\\" = p_id;\\r\\n\\r\\n\\t\\tupdate withdraw \\r\\n\\t\\tset \\\"status\\\" = 'PENDING'  where \\\"id\\\" = p_id;\\r\\n\\t\\tRAISE NOTICE 'whitdrawID: %',p_id;\\r\\n\\r\\n\\tend if;\\r\\n\\r\\n\\treturn v_exist;\\r\\n\\r\\n\\tEXCEPTION\\r\\n        -- Captura de excepciones\\r\\n        WHEN others THEN\\r\\n            -- Manejo de la excepción\\r\\n            RAISE NOTICE 'Error: %', SQLERRM;\\r\\n\\t\\t\\tINSERT INTO public.temp_log\\r\\n\\t\\t\\t    (id, process, \\\"method\\\", description, \\\"date\\\")\\r\\n\\t\\t\\tVALUES\\r\\n\\t\\t\\t    (uuid_generate_v4(), 'DB', 'get_tx->' || COALESCE(p_id, 'unknown'), SQLERRM, now());\\r\\n\\r\\n    END;\\r\\n\\r\\n$function$\\n\",\n            \"CREATE OR REPLACE FUNCTION public.get_tx_bk(p_id integer)\\n RETURNS boolean\\n LANGUAGE plpgsql\\nAS $function$\\r\\ndeclare\\r\\n    v_tx varchar;\\r\\n    v_id_blockchain float;\\r\\n    v_exist boolean = false;\\r\\n\\tv_address varchar;\\r\\n\\tv_amount float;\\r\\n\\tv_fec TIMESTAMP;\\n    v_time_second numeric;\\r\\n\\r\\nbegin\\r\\n\\tRAISE NOTICE 'Init whitdrawID: %',p_id;\\r\\n\\tif (p_id is null) then \\r\\n\\t\\tv_exist = false;\\r\\n\\t\\treturn v_exist; \\r\\n\\tend if;\\r\\n\\t/*\\r\\n\\t* Process: Identificion de transacion alfredPay.\\r\\n\\t* Descripcion: este proceso permite ubicar la transaccion con el fin\\r\\n\\t* de validar si la mima se rechaza o no en tal caso de que no consiga merge con la tabla contract_event.\\r\\n\\t*/\\r\\n\\tSELECT bi.address, w.\\\"createdAt\\\" AS fec, t.amount, extract(epoch from w.\\\"createdAt\\\")\\n\\tINTO v_address, v_fec, v_amount, v_time_second\\r\\n\\tFROM withdraw w\\r\\n\\tJOIN transacction t ON w.\\\"transacctionId\\\" = t.id\\r\\n\\tJOIN invoice i ON t.\\\"invoiceId\\\" = i.id\\r\\n\\tJOIN business_interaction bi ON i.\\\"businessInteractionId\\\" = bi.id\\r\\n\\tWHERE w.id = p_id;\\r\\n\\r\\n\\tRAISE NOTICE 'Transaction value v_address % v_fec % v_amount % second %', v_address, v_fec, v_amount, v_time_second;\\r\\n\\n\\tSELECT tx, id \\n\\tINTO v_tx, v_id_blockchain \\n\\tFROM contract_event \\n\\tWHERE lower(\\\"from\\\")=lower(v_address) \\n\\tAND amount::float/1000000000000000000=v_amount\\n\\tAND \\\"date\\\" is not null\\n\\tAND cast(\\\"date\\\" as timestamp) at time zone 'utc' >= v_fec\\n\\tAND (extract(epoch from cast(\\\"date\\\" as timestamp) at time zone 'utc') - v_time_second) < 18600\\n\\tAND id not in (select id_blockchain from test_scripts) \\n\\tAND tx NOT IN (\\n\\t\\tSELECT t.\\\"txHash\\\"\\n\\t\\tFROM transacction t\\n\\t\\tJOIN invoice i ON t.\\\"invoiceId\\\" = i.id\\n\\t\\tJOIN business_interaction bi ON i.\\\"businessInteractionId\\\" = bi.id\\n\\t\\tWHERE lower(bi.address) = lower(v_address)\\n\\t\\tAND t.\\\"createdAt\\\" >= v_fec\\n\\t)\\n\\tLIMIT 1;\\n\\r\\n\\tRAISE NOTICE 'Transaction txHash % v_id_blockchain %', v_tx, v_id_blockchain;\\r\\n\\tif (v_tx is not null) then \\r\\n\\r\\n\\t\\tv_exist = true;\\r\\n\\t\\tinsert into test_scripts \\r\\n\\t\\t(id, tx, id_blockchain, fecha) values(p_id, v_tx, v_id_blockchain, cast(v_fec as date)); \\r\\n\\r\\n\\t\\tupdate transacction \\r\\n\\t\\tset \\\"txHash\\\" = v_tx  where \\\"withdrawId\\\" = p_id;\\r\\n\\r\\n\\t\\tupdate withdraw \\r\\n\\t\\tset \\\"status\\\" = 'PENDING'  where \\\"id\\\" = p_id;\\r\\n\\t\\tRAISE NOTICE 'whitdrawID: %',p_id;\\r\\n\\r\\n\\tend if;\\r\\n\\r\\n\\treturn v_exist;\\r\\n\\r\\n\\tEXCEPTION\\r\\n        -- Captura de excepciones\\r\\n        WHEN others THEN\\r\\n            -- Manejo de la excepción\\r\\n            RAISE NOTICE 'Error: %', SQLERRM;\\r\\n    END;\\r\\n\\r\\n$function$\\n\",\n            \"CREATE OR REPLACE FUNCTION public.get_webhook_queues()\\n RETURNS TABLE(id uuid, \\\"transactionId\\\" uuid, \\\"typeTransaction\\\" character varying, status character varying, \\\"statusTransaction\\\" character varying, \\\"eventData\\\" json, metadata json, \\\"createdAt\\\" timestamp with time zone, \\\"updatedAt\\\" timestamp with time zone, attempts integer, reattempt_interval integer)\\n LANGUAGE plpgsql\\nAS $function$\\r\\nDECLARE\\r\\n    reattempt_intervals INT[] := ARRAY[10 * 60000, 20 * 60000, 40 * 60000, 80 * 60000];\\r\\nBEGIN\\r\\n    RETURN QUERY\\r\\n    SELECT\\r\\n        \\\"wq\\\".\\\"id\\\",\\r\\n        \\\"wq\\\".\\\"transactionId\\\",\\r\\n        \\\"wq\\\".\\\"typeTransaction\\\",\\r\\n        \\\"wq\\\".\\\"status\\\",\\r\\n        \\\"wq\\\".\\\"statusTransaction\\\",\\r\\n        \\\"wq\\\".\\\"eventData\\\",\\r\\n        \\\"wq\\\".\\\"metadata\\\",\\r\\n        \\\"wq\\\".\\\"createdAt\\\",\\r\\n        \\\"wq\\\".\\\"updatedAt\\\",\\r\\n        \\\"wq\\\".\\\"attempts\\\",\\r\\n        reattempt_intervals[COALESCE(\\\"wq\\\".\\\"attempts\\\", 1)]\\r\\n    FROM\\r\\n        \\\"webhook_queue\\\" \\\"wq\\\"\\r\\n    WHERE\\r\\n        \\\"wq\\\".\\\"status\\\" = 'FAILED'\\r\\n        AND COALESCE(\\\"wq\\\".\\\"attempts\\\", 1) < 5\\r\\n        AND (extract(epoch from now()) * 1000 - extract(epoch from \\\"wq\\\".\\\"updatedAt\\\") * 1000) >= reattempt_intervals[COALESCE(\\\"wq\\\".\\\"attempts\\\", 1)]\\r\\n    LIMIT 100;\\r\\nEND;\\r\\n$function$\\n\",\n            \"CREATE OR REPLACE FUNCTION public.insert_exchange_factors_unique(p_business_id integer)\\n RETURNS void\\n LANGUAGE plpgsql\\nAS $function$\\r\\nBEGIN\\r\\n    -- Validar que no exista businessId duplicado\\r\\n    IF EXISTS (SELECT 1 FROM public.exchange_factor WHERE \\\"businessId\\\" = p_business_id) THEN\\r\\n        RAISE EXCEPTION 'Ya existe un registro con businessId = %', p_business_id;\\r\\n    END IF;\\r\\n\\r\\n    -- Inserciones con los valores que proporcionaste\\r\\n    INSERT INTO public.exchange_factor (from_currency, to_currency, rate, percent, \\\"businessId\\\")\\r\\n    VALUES\\r\\n    ('ARS', 'USDT', 1210.23, '-0.6', p_business_id),\\r\\n    ('ARS', 'USDC', 1311.44, '-0.6', p_business_id),\\r\\n    ('BRL', 'USDC', 5.57, '0', p_business_id),\\r\\n    ('BRL', 'USDT', 5.57, '0', p_business_id),\\r\\n    ('COP', 'USDC', 4242, '0', p_business_id),\\r\\n    ('COP', 'USDT', 4242, '0', p_business_id),\\r\\n    ('DOP', 'USDC', 58.64, '0', p_business_id),\\r\\n    ('DOP', 'USDT', 58.64, '0', p_business_id),\\r\\n    ('HK_USD', 'USDC', 1, '0', p_business_id),\\r\\n    ('HK_USD', 'USDC', 1, '0', p_business_id),\\r\\n    ('HKD', 'USDT', 7.77, '0', p_business_id),\\r\\n    ('HKD', 'HKD', 1, '0', p_business_id),\\r\\n    ('HKD', 'MXN', 2.54, '0', p_business_id),\\r\\n    ('HKD', 'USDC', 7.77, '0', p_business_id),\\r\\n    ('MXN', 'USDT', 20.67, '-2', p_business_id),\\r\\n    ('MXN', 'HK_USD', 7.85, '0', p_business_id),\\r\\n    ('MXN', 'HKD', 0.39, '0', p_business_id),\\r\\n    ('MXN', 'USDC', 19.24, '-2', p_business_id),\\r\\n    ('USD', 'USDC', 1, '0', p_business_id),\\r\\n    ('USD', 'USDT', 1, '0', p_business_id),\\r\\n    ('USDC', 'CLP', 4127.44, '0', p_business_id),\\r\\n    ('USDC', 'GTQ', 7.79, '0', p_business_id),\\r\\n    ('USDC', 'DOP', 58.64, '0', p_business_id),\\r\\n    ('USDC', 'HKD', 7.77, '0', p_business_id),\\r\\n    ('USDC', 'COP', 4158, '0', p_business_id),\\r\\n    ('USDC', 'BRL', 5.57, '0', p_business_id),\\r\\n    ('USDC', 'MXN', 18.49, '0', p_business_id),\\r\\n    ('USDC', 'ARS', 1270.12, '0.6', p_business_id),\\r\\n    ('USDT', 'MXN', 20.41, '0', p_business_id),\\r\\n    ('USDT', 'BRL', 5.57, '0', p_business_id),\\r\\n    ('USDT', 'HKD', 7.77, '0', p_business_id),\\r\\n    ('USDT', 'DOP', 0.017, '0', p_business_id),\\r\\n    ('USDT', 'COP', 4158, '0', p_business_id),\\r\\n    ('USDT', 'ARS', 1134.43, '0.6', p_business_id);\\r\\n\\r\\nEND;\\r\\n$function$\\n\",\n            \"CREATE OR REPLACE FUNCTION public.insert_exchange_factors_unique_by_offramp(p_business_id integer, p_country character varying)\\n RETURNS void\\n LANGUAGE plpgsql\\nAS $function$\\r\\nBEGIN\\r\\n    -- Inserción condicional: USDT/USDT\\r\\n    IF NOT EXISTS (\\r\\n        SELECT 1\\r\\n        FROM public.exchange_factor\\r\\n        WHERE \\\"businessId\\\" = p_business_id\\r\\n          AND from_currency = 'USDT'\\r\\n          AND to_currency = p_country\\r\\n    ) THEN\\r\\n        INSERT INTO public.exchange_factor (from_currency, to_currency, rate, percent, \\\"businessId\\\")\\r\\n        VALUES ('USDT', p_country, 12.00, '0', p_business_id);\\r\\n    END IF;\\r\\n\\r\\n    -- Inserción condicional: USDC/USDC\\r\\n    IF NOT EXISTS (\\r\\n        SELECT 1\\r\\n        FROM public.exchange_factor\\r\\n        WHERE \\\"businessId\\\" = p_business_id\\r\\n          AND from_currency = 'USDC'\\r\\n          AND to_currency = p_country\\r\\n    ) THEN\\r\\n        INSERT INTO public.exchange_factor (from_currency, to_currency, rate, percent, \\\"businessId\\\")\\r\\n        VALUES ('USDC', p_country, 12.00, '0', p_business_id);\\r\\n    END IF;\\r\\n\\r\\nEND;\\r\\n$function$\\n\",\n            \"CREATE OR REPLACE FUNCTION public.insert_history_operation_liquidity(p_process character varying, p_id_transaction character varying, p_response jsonb, p_quote_buy numeric, p_quote_sell numeric)\\n RETURNS void\\n LANGUAGE plpgsql\\nAS $function$\\nDECLARE\\n    v_revenue NUMERIC;\\n    v_side TEXT;\\nBEGIN\\n\\n\\t-- Cálculo del revenue según el side\\n\\t    IF v_side = 'sell' THEN\\n\\t        -- Invertir el cálculo para evitar negativo\\n\\t       v_revenue := TRUNC(((p_quote_sell - p_quote_buy) / p_quote_buy) * 10000, 2);\\n\\t    ELSE\\n\\t        -- Caso buy (default)\\n\\t        v_revenue := TRUNC(((p_quote_buy - p_quote_sell) / p_quote_sell) * 10000, 2);\\n\\t    END IF;\\n\\t\\t\\t\\n\\n    INSERT INTO history_operation_liquidity (\\n        process,\\n        idTransaction,\\n        response,\\n        revenue,\\n        created_at,\\n        updated_at\\n    )\\n    VALUES (\\n        p_process,\\n        p_id_transaction,\\n        p_response,\\n        v_revenue::VARCHAR,\\n        NOW(),\\n        NOW()\\n    );\\nEND;\\n$function$\\n\",\n            \"CREATE OR REPLACE FUNCTION public.is_address_excluded(p_address character varying, p_chain character varying)\\n RETURNS boolean\\n LANGUAGE plpgsql\\nAS $function$\\r\\nDECLARE\\r\\n    exists_record BOOLEAN;\\r\\nBEGIN\\r\\n    SELECT EXISTS (\\r\\n        SELECT 1\\r\\n        FROM public.excluded_addresses ea\\r\\n        WHERE ea.address = p_address\\r\\n        AND (ea.chain = p_chain OR ea.chain IS NULL)\\r\\n    )\\r\\n    INTO exists_record;\\r\\n\\r\\n    RETURN exists_record;\\r\\nEND;\\r\\n$function$\\n\",\n            \"CREATE OR REPLACE FUNCTION public.kyc_status_count(statuskyc character varying, country character varying)\\n RETURNS TABLE(count bigint, kycstatus character varying)\\n LANGUAGE plpgsql\\nAS $function$\\r\\nBEGIN\\r\\n    RETURN QUERY\\r\\n    SELECT COUNT(*), ic.\\\"statusKyc\\\"\\r\\n    FROM individual_customers ic\\r\\n    WHERE ic.\\\"statusKyc\\\" = $1 AND ic.country = $2\\r\\n    GROUP BY ic.\\\"statusKyc\\\";\\r\\nEND; $function$\\n\",\n            \"CREATE OR REPLACE FUNCTION public.kycstatuscirclebydate(p_date date)\\n RETURNS TABLE(country text, statuskyc text, count bigint)\\n LANGUAGE plpgsql\\nAS $function$\\r\\nBEGIN\\r\\n    RETURN QUERY\\r\\n    SELECT \\r\\n        ic.country,\\r\\n        ic.\\\"statusKyc\\\",\\r\\n        count(*) AS count\\r\\n    FROM \\r\\n        individual_customers ic\\r\\n    WHERE \\r\\n        ic.\\\"createdAt\\\" >= p_date\\r\\n    GROUP BY \\r\\n        ic.\\\"statusKyc\\\", ic.country;\\r\\nEND;\\r\\n$function$\\n\",\n            \"CREATE OR REPLACE FUNCTION public.registerpaymentwebhookqueuewld(p_data jsonb)\\n RETURNS boolean\\n LANGUAGE plpgsql\\nAS $function$\\r\\nDECLARE \\r\\n\\tv_valid_withdraw integer;\\r\\n\\tv_statusWithdraw withdraw_status_enum;\\r\\nBEGIN\\r\\n\\tv_valid_withdraw := 0;\\r\\n\\tv_statusWithdraw := p_data->>'statusWithdraw';\\r\\n\\r\\n\\tRAISE NOTICE 'id %', p_data->>'withdrawId';\\r\\n\\r\\n\\tBEGIN\\r\\n\\t\\tSELECT w.id \\r\\n\\t\\tINTO v_valid_withdraw \\r\\n\\t\\tFROM withdraw w \\r\\n\\t\\tWHERE w.id = CAST(p_data->>'withdrawId' AS numeric)\\r\\n\\t\\tAND w.status = 'PENDING';\\r\\n\\tEXCEPTION\\r\\n\\t\\tWHEN NO_DATA_FOUND THEN\\r\\n\\t\\t\\tv_valid_withdraw := 0;\\r\\n\\tEND;\\r\\n\\r\\n\\tIF v_valid_withdraw = 0 THEN \\r\\n\\t\\tRETURN false;\\r\\n\\tEND IF;\\r\\n\\r\\n\\tRAISE NOTICE 'eventData %', p_data->>'eventData';\\r\\n\\tINSERT INTO public.webhook_queue_wld\\r\\n\\t(\\r\\n\\t\\tid, \\r\\n\\t\\t\\\"withdrawId\\\", \\r\\n\\t\\t\\\"typeTransaction\\\", \\r\\n\\t\\t\\\"statusWithdraw\\\", \\r\\n\\t\\t\\\"status\\\",\\r\\n\\t\\t\\\"eventData\\\", \\r\\n\\t\\t\\\"metadata\\\", \\r\\n\\t\\t\\\"proccess\\\", \\r\\n\\t\\t\\\"createdAt\\\", \\r\\n\\t\\t\\\"updatedAt\\\",\\r\\n\\t\\t\\\"eventOperation\\\",\\r\\n\\t\\t\\\"businessInterationId\\\"\\r\\n\\t)\\r\\n\\tVALUES (\\r\\n\\t\\tuuid_generate_v4(),\\r\\n\\t\\tCAST(p_data->>'withdrawId' AS integer), \\r\\n\\t\\tp_data->>'typeTransaction',\\r\\n\\t\\tp_data->>'statusWithdraw',\\r\\n\\t\\tp_data->>'status',\\r\\n\\t\\t(p_data->>'eventData')::json,\\r\\n\\t\\t(p_data->>'metadata')::json, \\r\\n\\t\\tp_data->>'proccess',\\r\\n\\t\\tNOW(), \\r\\n\\t\\tNOW(),\\r\\n\\t\\tp_data->>'eventOperation',\\r\\n\\t\\tnull\\r\\n\\t);\\r\\n\\r\\n\\tUPDATE withdraw \\r\\n\\tSET status = v_statusWithdraw\\r\\n\\tWHERE id = CAST(p_data->>'withdrawId' AS integer);\\r\\n\\r\\n\\tRETURN true;\\r\\nEND;\\r\\n$function$\\n\",\n            \"CREATE OR REPLACE FUNCTION public.search_consilation_transaction_blockchain(p_id integer)\\n RETURNS boolean\\n LANGUAGE plpgsql\\nAS $function$\\r\\ndeclare\\r\\n    v_tx varchar;\\r\\n    v_id_blockchain float;\\r\\n    v_exist boolean = false;\\r\\n\\tv_address varchar;\\r\\n\\tv_amount float;\\r\\n\\tv_fec TIMESTAMP;\\r\\n    v_time_second numeric;\\r\\n\\r\\nbegin\\r\\n\\tRAISE NOTICE 'Init whitdrawID: %',p_id;\\r\\n\\tif (p_id is null) then \\r\\n\\t\\tv_exist = false;\\r\\n\\t\\treturn v_exist; \\r\\n\\tend if;\\r\\n\\t/*\\r\\n\\t* Process: Identificion de transacion alfredPay.\\r\\n\\t* Descripcion: este proceso permite ubicar la transaccion con el fin\\r\\n\\t* de validar si la mima se rechaza o no en tal caso de que no consiga merge con la tabla contract_event.\\r\\n\\t*/\\r\\n\\tSELECT bi.address, w.\\\"createdAt\\\" AS fec, t.amount, extract(epoch from w.\\\"createdAt\\\")\\r\\n\\tINTO v_address, v_fec, v_amount, v_time_second\\r\\n\\tFROM withdraw w\\r\\n\\tJOIN transacction t ON w.\\\"transacctionId\\\" = t.id\\r\\n\\tJOIN invoice i ON t.\\\"invoiceId\\\" = i.id\\r\\n\\tJOIN business_interaction bi ON i.\\\"businessInteractionId\\\" = bi.id\\r\\n\\tWHERE w.id = p_id;\\r\\n\\r\\n\\tRAISE NOTICE 'Transaction value v_address % v_fec % v_amount % second %', v_address, v_fec, v_amount, v_time_second;\\r\\n\\r\\n\\tSELECT tx, id \\r\\n\\tINTO v_tx, v_id_blockchain \\r\\n\\tFROM contract_event \\r\\n\\tWHERE lower(\\\"from\\\")=lower(v_address) \\r\\n\\tAND amount::float/1000000000000000000=v_amount\\r\\n\\tAND \\\"date\\\" is not null\\r\\n\\tAND cast(\\\"date\\\" as timestamp) at time zone 'utc' >= v_fec\\r\\n\\tAND (extract(epoch from cast(\\\"date\\\" as timestamp) at time zone 'utc') - v_time_second) < 18600\\r\\n\\tAND id not in (select id_blockchain from test_scripts) \\r\\n\\tAND tx NOT IN (\\r\\n\\t\\tSELECT t.\\\"txHash\\\"\\r\\n\\t\\tFROM transacction t\\r\\n\\t\\tJOIN invoice i ON t.\\\"invoiceId\\\" = i.id\\r\\n\\t\\tJOIN business_interaction bi ON i.\\\"businessInteractionId\\\" = bi.id\\r\\n\\t\\tWHERE lower(bi.address) = lower(v_address)\\r\\n\\t\\tAND t.\\\"createdAt\\\" >= v_fec\\r\\n\\t)\\r\\n\\tLIMIT 1;\\r\\n\\r\\n\\tRAISE NOTICE 'Transaction txHash % v_id_blockchain %', v_tx, v_id_blockchain;\\r\\n\\tif (v_tx is not null) then \\r\\n\\r\\n\\t\\tv_exist = true;\\r\\n\\t\\tinsert into test_scripts \\r\\n\\t\\t(id, tx, id_blockchain, fecha) values(p_id, v_tx, v_id_blockchain, cast(v_fec as date)); \\r\\n\\r\\n\\t\\tupdate transacction \\r\\n\\t\\tset \\\"txHash\\\" = v_tx  where \\\"withdrawId\\\" = p_id;\\r\\n\\r\\n\\t\\tupdate withdraw \\r\\n\\t\\tset \\\"status\\\" = 'PENDING'  where \\\"id\\\" = p_id;\\r\\n\\t\\tRAISE NOTICE 'whitdrawID: %',p_id;\\r\\n\\r\\n\\tend if;\\r\\n\\r\\n\\treturn v_exist;\\r\\n\\r\\n\\tEXCEPTION\\r\\n        -- Captura de excepciones\\r\\n        WHEN others THEN\\r\\n            -- Manejo de la excepción\\r\\n            RAISE NOTICE 'Error: %', SQLERRM;\\r\\n    END;\\r\\n\\r\\n$function$\\n\",\n            \"CREATE OR REPLACE FUNCTION public.update_composite_quote_updated_at()\\n RETURNS trigger\\n LANGUAGE plpgsql\\nAS $function$\\nBEGIN\\n    NEW.\\\"updatedAt\\\" = CURRENT_TIMESTAMP;\\n    RETURN NEW;\\nEND;\\n$function$\\n\",\n            \"CREATE OR REPLACE FUNCTION public.update_payin_updated_at()\\n RETURNS trigger\\n LANGUAGE plpgsql\\nAS $function$\\nBEGIN\\n  NEW.updated_at = NOW();\\n  RETURN NEW;\\nEND;\\n$function$\\n\",\n            \"CREATE OR REPLACE FUNCTION public.update_payout_updated_at()\\n RETURNS trigger\\n LANGUAGE plpgsql\\nAS $function$\\nBEGIN\\n  NEW.updated_at = NOW();\\n  RETURN NEW;\\nEND;\\n$function$\\n\",\n            \"CREATE OR REPLACE FUNCTION public.update_transfer_updated_at()\\n RETURNS trigger\\n LANGUAGE plpgsql\\nAS $function$\\nBEGIN\\n  NEW.updated_at = NOW();\\n  RETURN NEW;\\nEND;\\n$function$\\n\",\n            \"CREATE OR REPLACE FUNCTION public.update_updated_at_column()\\n RETURNS trigger\\n LANGUAGE plpgsql\\nAS $function$\\nBEGIN\\n  NEW.updated_at = NOW();\\n  RETURN NEW;\\nEND;\\n$function$\\n\",\n            \"CREATE OR REPLACE FUNCTION public.update_updatedat_column()\\n RETURNS trigger\\n LANGUAGE plpgsql\\nAS $function$\\nBEGIN\\n    NEW.updatedAt = CURRENT_TIMESTAMP;\\n    RETURN NEW;\\nEND;\\n$function$\\n\",\n            \"CREATE OR REPLACE FUNCTION public.update_webhook_queue_v2_updated_at()\\n RETURNS trigger\\n LANGUAGE plpgsql\\nAS $function$\\nBEGIN\\n  NEW.updated_at = NOW();\\n  RETURN NEW;\\nEND;\\n$function$\\n\",\n            \"CREATE OR REPLACE FUNCTION public.updateonrampbystatusandcurrency(p_action integer, p_status character varying, p_currency character varying)\\n RETURNS jsonb[]\\n LANGUAGE plpgsql\\nAS $function$\\r\\nDECLARE \\r\\n    c_paymentPending jsonb;\\r\\n    c_result jsonb[] := '{}';\\r\\nBEGIN\\r\\n    FOR c_paymentPending IN \\r\\n        SELECT jsonb_build_object(\\r\\n            'id', or2.id,\\r\\n            'txHash', or2.\\\"txHash\\\",\\r\\n            'address', or2.\\\"depositAddress\\\",\\r\\n            'toAmount', q.\\\"toAmount\\\",\\r\\n            'chain', q.\\\"chain\\\",\\r\\n            'contador', or2.\\\"totalSend\\\"\\r\\n        )\\r\\n\\t    FROM \\r\\n\\t       on_ramps or2 \\r\\n\\t    INNER JOIN \\r\\n\\t        \\\"quote\\\" q ON or2.\\\"quote\\\" = q.id\\r\\n\\t    WHERE \\r\\n\\t        or2.\\\"fiatPaymentInstructionsId\\\" % 2 = p_action\\r\\n\\t\\t\\tAND or2.status = p_status::on_ramps_status_enum\\r\\n\\t\\t\\tAND q.\\\"fromCurrency\\\"::varchar = p_currency::varchar\\r\\n\\t\\t\\tand or2.\\\"txHash\\\" is not null\\r\\n\\t\\t\\tand or2.\\\"totalSend\\\" = 1\\r\\n\\t    ORDER BY \\r\\n\\t     \\tor2.\\\"fiatPaymentInstructionsId\\\" ASC\\r\\n\\t    LIMIT 500\\r\\n    LOOP\\r\\n        c_result := array_append(c_result, c_paymentPending);\\r\\n    END LOOP;\\r\\n   \\r\\n    RETURN c_result;\\r\\nEND;\\r\\n$function$\\n\",\n            \"CREATE OR REPLACE FUNCTION public.usuarios_por_status(status character varying, country character varying)\\n RETURNS TABLE(count bigint, statu character varying)\\n LANGUAGE plpgsql\\nAS $function$\\r\\nBEGIN\\r\\n    RETURN QUERY\\r\\n    SELECT COUNT(*), ic.\\\"statusKyc\\\"\\r\\n    FROM individual_customers ic\\r\\n    WHERE ic.\\\"statusKyc\\\" = $1 AND ic.country = $2\\r\\n    GROUP BY ic.\\\"statusKyc\\\";\\r\\nEND; $function$\\n\"\n          ]\n        ]\n      }\n    ]\n  }\n}"
  }
]